{"version":1,"resource":"vscode-remote://wsl%2Bubuntu/home/jaden/myportfolio/portfolio/src/components/Sidebar/index.scss","entries":[{"id":"Rk5l.scss","timestamp":1674596673085},{"id":"osdM.scss","timestamp":1674597509925},{"id":"xz4Z.scss","timestamp":1674608055695},{"id":"h9xf.scss","timestamp":1674608450935},{"id":"U9rX.scss","timestamp":1674608659385},{"id":"RQwG.scss","timestamp":1674608947365},{"id":"BUEN.scss","timestamp":1674608988955},{"id":"cuup.scss","timestamp":1674688351739},{"id":"QzJc.scss","timestamp":1674689664669},{"id":"5fVp.scss","timestamp":1674689721339},{"id":"yJvg.scss","timestamp":1674689785999},{"id":"7SSt.scss","timestamp":1674689828529},{"id":"VPx3.scss","timestamp":1674689843919},{"id":"N0T0.scss","timestamp":1674689867619},{"id":"VV12.scss","timestamp":1674689899909},{"id":"Px7c.scss","timestamp":1674689931079},{"id":"vvld.scss","timestamp":1674689948519},{"id":"EON6.scss","timestamp":1674691280859},{"id":"oGXP.scss","source":"undoRedo.source","timestamp":1674691283129},{"id":"w4l1.scss","timestamp":1674691292359},{"id":"C92G.scss","source":"undoRedo.source","timestamp":1674691295039},{"id":"7STz.scss","timestamp":1674691319979},{"id":"Kdvv.scss","timestamp":1674691383109},{"id":"99oV.scss","timestamp":1675039178038}]}